LICENSE-HQC.md
MANIFEST.in
README.md
pyproject.toml
setup.py
cffi_modules/hqc-128_clean.py
cffi_modules/hqc-192_clean.py
cffi_modules/hqc-256_clean.py
lib/PQClean/crypto_kem/hqc-128/clean/code.c
lib/PQClean/crypto_kem/hqc-128/clean/fft.c
lib/PQClean/crypto_kem/hqc-128/clean/gf.c
lib/PQClean/crypto_kem/hqc-128/clean/gf2x.c
lib/PQClean/crypto_kem/hqc-128/clean/hqc.c
lib/PQClean/crypto_kem/hqc-128/clean/kem.c
lib/PQClean/crypto_kem/hqc-128/clean/parsing.c
lib/PQClean/crypto_kem/hqc-128/clean/reed_muller.c
lib/PQClean/crypto_kem/hqc-128/clean/reed_solomon.c
lib/PQClean/crypto_kem/hqc-128/clean/shake_ds.c
lib/PQClean/crypto_kem/hqc-128/clean/shake_prng.c
lib/PQClean/crypto_kem/hqc-128/clean/vector.c
lib/PQClean/crypto_kem/hqc-128/clean/../../../common/fips202.c
lib/PQClean/crypto_kem/hqc-128/clean/../../../common/randombytes.c
lib/PQClean/crypto_kem/hqc-128/clean/../../../common/sha2.c
lib/PQClean/crypto_kem/hqc-192/clean/code.c
lib/PQClean/crypto_kem/hqc-192/clean/fft.c
lib/PQClean/crypto_kem/hqc-192/clean/gf.c
lib/PQClean/crypto_kem/hqc-192/clean/gf2x.c
lib/PQClean/crypto_kem/hqc-192/clean/hqc.c
lib/PQClean/crypto_kem/hqc-192/clean/kem.c
lib/PQClean/crypto_kem/hqc-192/clean/parsing.c
lib/PQClean/crypto_kem/hqc-192/clean/reed_muller.c
lib/PQClean/crypto_kem/hqc-192/clean/reed_solomon.c
lib/PQClean/crypto_kem/hqc-192/clean/shake_ds.c
lib/PQClean/crypto_kem/hqc-192/clean/shake_prng.c
lib/PQClean/crypto_kem/hqc-192/clean/vector.c
lib/PQClean/crypto_kem/hqc-192/clean/../../../common/fips202.c
lib/PQClean/crypto_kem/hqc-192/clean/../../../common/randombytes.c
lib/PQClean/crypto_kem/hqc-192/clean/../../../common/sha2.c
lib/PQClean/crypto_kem/hqc-256/clean/code.c
lib/PQClean/crypto_kem/hqc-256/clean/fft.c
lib/PQClean/crypto_kem/hqc-256/clean/gf.c
lib/PQClean/crypto_kem/hqc-256/clean/gf2x.c
lib/PQClean/crypto_kem/hqc-256/clean/hqc.c
lib/PQClean/crypto_kem/hqc-256/clean/kem.c
lib/PQClean/crypto_kem/hqc-256/clean/parsing.c
lib/PQClean/crypto_kem/hqc-256/clean/reed_muller.c
src/pypqc_cffi_bindings_hqc.egg-info/PKG-INFO
src/pypqc_cffi_bindings_hqc.egg-info/SOURCES.txt
src/pypqc_cffi_bindings_hqc.egg-info/dependency_links.txt
src/pypqc_cffi_bindings_hqc.egg-info/requires.txt
src/pypqc_cffi_bindings_hqc.egg-info/top_level.txt