Metadata-Version: 2.1
Name: pypqc-cffi-bindings-hqc
Version: 0.0.1.dev0
License: I, Philippe Gaborit, University of Limoges, 123 av. A. Thomas, 87000 Limoges France
Classifier: License :: Other/Proprietary License
Classifier: License :: Public Domain
License-File: LICENSE-HQC.md
Requires-Dist: cffi>=1.0.0; platform_python_implementation != "PyPy"
